unity_sds_apgs_client/__init__.py
unity_sds_apgs_client/api/__init__.py
unity_sds_apgs_client/api/default_api.py
unity_sds_apgs_client/api_client.py
unity_sds_apgs_client/api_response.py
unity_sds_apgs_client/configuration.py
unity_sds_apgs_client/exceptions.py
unity_sds_apgs_client/models/__init__.py
unity_sds_apgs_client/models/ads_acb_mcp_clone_get200_response.py
unity_sds_apgs_client/py.typed
unity_sds_apgs_client/rest.py
unity_sds_apgs_client-0.1.0.dist-info/METADATA
unity_sds_apgs_client-0.1.0.dist-info/WHEEL
unity_sds_apgs_client-0.1.0.dist-info/RECORD
